scicomap/__init__.py
scicomap/cblind.py
scicomap/cmath.py
scicomap/datasets.py
scicomap/scicomap.py
scicomap/utils.py
scicomap/data/grmhd.png
scicomap/data/jacksboro_fault_dem.npz
scicomap/data/s1045.ima.gz
scicomap/data/tng.jpg
scicomap/data/vortex.jpg
scicomap-1.0.1.dist-info/LICENSE.md
scicomap-1.0.1.dist-info/METADATA
scicomap-1.0.1.dist-info/WHEEL
scicomap-1.0.1.dist-info/top_level.txt
scicomap-1.0.1.dist-info/RECORD
