Metadata-Version: 2.1
Name: scicomap
Version: 1.0.1
Summary: data visualization on maps with varying levels of granularity
Author-email: Thomas Bury <bury.thomas@gmail.com>
License: MIT License
Project-URL: homepage, https://github.com/ThomasBury/scicomap
Project-URL: documentation, https://github.com/ThomasBury/scicomap
Project-URL: repository, https://github.com/ThomasBury/scicomap.git
Project-URL: changelog, https://github.com/ThomasBury/scicomap
Project-URL: Tracker, https://github.com/ThomasBury/scicomap/issues
Keywords: visualization,color,uniform,scientific
Classifier: Programming Language :: Python :: 3
Requires-Python: >=3.10
License-File: LICENSE.md
Requires-Dist: numpy
Requires-Dist: pandas
Requires-Dist: scipy
Requires-Dist: colorspacious
Requires-Dist: colorcet
Requires-Dist: cmcrameri
Requires-Dist: cmocean
Requires-Dist: cmasher >=1.5.8
Requires-Dist: palettable >=3.3.0
Requires-Dist: matplotlib >=3.3.0
Provides-Extra: doc
Requires-Dist: ipykernel ; extra == 'doc'
Requires-Dist: ipython-genutils ; extra == 'doc'
Requires-Dist: pandoc ; extra == 'doc'
Requires-Dist: sphinx ; extra == 'doc'
Requires-Dist: sphinxawesome-theme ==5.0.0b5 ; extra == 'doc'
Requires-Dist: nbsphinx ; extra == 'doc'
Requires-Dist: sphinx-autodoc-typehints ; extra == 'doc'
Requires-Dist: sphinx-copybutton ; extra == 'doc'
Requires-Dist: sphinx-tabs ; extra == 'doc'
Provides-Extra: lint
Requires-Dist: black ; extra == 'lint'
Requires-Dist: flake8 ; extra == 'lint'
Provides-Extra: test
Requires-Dist: pytest ; extra == 'test'
Requires-Dist: pytest-cov ; extra == 'test'
